Compiled from "Test1.java"
public class generic.type_inference.Test1 {
  public generic.type_inference.Test1();
    descriptor: ()V
    Code:
       0: aload_0
       1: invokespecial #1                  // Method java/lang/Object."<init>":()V
       4: return

  public static void main(java.lang.String[]);
    descriptor: ([Ljava/lang/String;)V
    Code:
       0: ldc           #2                  // String d
       2: new           #3                  // class java/util/ArrayList
       5: dup
       6: invokespecial #4                  // Method java/util/ArrayList."<init>":()V
       9: invokestatic  #5                  // Method pick:(Ljava/lang/Object;Ljava/lang/Object;)Ljava/lang/Object;
      12: checkcast     #6                  // class java/io/Serializable
      15: astore_1
      16: return

  static <T> T pick(T, T);
    descriptor: (Ljava/lang/Object;Ljava/lang/Object;)Ljava/lang/Object;
    Code:
       0: aload_1
       1: areturn
}
