Compiled from "Test1.java"
public class generic.type_safety.Test1 {
  public generic.type_safety.Test1();
    descriptor: ()V
    Code:
       0: aload_0
       1: invokespecial #1                  // Method java/lang/Object."<init>":()V
       4: return

  public void main(java.lang.String[]);
    descriptor: ([Ljava/lang/String;)V
    Code:
       0: new           #2                  // class generic/type_safety/Pair
       3: dup
       4: ldc           #3                  // String James
       6: ldc           #4                  // String Jiang
       8: invokespecial #5                  // Method generic/type_safety/Pair."<init>":(Ljava/lang/Object;Ljava/lang/Object;)V
      11: astore_2
      12: aload_2
      13: invokevirtual #6                  // Method generic/type_safety/Pair.getFirst:()Ljava/lang/Object;
      16: checkcast     #7                  // class java/lang/String
      19: astore_3
      20: getstatic     #8                  // Field java/lang/System.out:Ljava/io/PrintStream;
      23: new           #9                  // class java/lang/StringBuilder
      26: dup
      27: invokespecial #10                 // Method java/lang/StringBuilder."<init>":()V
      30: ldc           #11                 // String first:
      32: invokevirtual #12                 // Method java/lang/StringBuilder.append:(Ljava/lang/String;)Ljava/lang/StringBuilder;
      35: aload_3
      36: invokevirtual #12                 // Method java/lang/StringBuilder.append:(Ljava/lang/String;)Ljava/lang/StringBuilder;
      39: invokevirtual #13                 // Method java/lang/StringBuilder.toString:()Ljava/lang/String;
      42: invokevirtual #14                 // Method java/io/PrintStream.println:(Ljava/lang/String;)V
      45: return
}
