Classfile /d:/demos/java_demo/src/generic/type_safety/Test.class
  Last modified 2016-1-30; size 789 bytes
  MD5 checksum dce4bf6bd568fcac5e801b4159a4a6f4
  Compiled from "Test.java"
public class generic.type_safety.Test
  minor version: 0
  major version: 52
  flags: ACC_PUBLIC, ACC_SUPER
Constant pool:
   #1 = Methodref          #16.#25        // java/lang/Object."<init>":()V
   #2 = Class              #26            // generic/type_safety/Pair
   #3 = String             #27            // James
   #4 = String             #28            // Jiang
   #5 = Methodref          #2.#29         // generic/type_safety/Pair."<init>":(Ljava/lang/Object;Ljava/lang/Object;)V
   #6 = Methodref          #2.#30         // generic/type_safety/Pair.getFirst:()Ljava/lang/Object;
   #7 = Class              #31            // java/lang/String
   #8 = Fieldref           #32.#33        // java/lang/System.out:Ljava/io/PrintStream;
   #9 = Class              #34            // java/lang/StringBuilder
  #10 = Methodref          #9.#25         // java/lang/StringBuilder."<init>":()V
  #11 = String             #35            // first:
  #12 = Methodref          #9.#36         // java/lang/StringBuilder.append:(Ljava/lang/String;)Ljava/lang/StringBuilder;
  #13 = Methodref          #9.#37         // java/lang/StringBuilder.toString:()Ljava/lang/String;
  #14 = Methodref          #38.#39        // java/io/PrintStream.println:(Ljava/lang/String;)V
  #15 = Class              #40            // generic/type_safety/Test
  #16 = Class              #41            // java/lang/Object
  #17 = Utf8               <init>
  #18 = Utf8               ()V
  #19 = Utf8               Code
  #20 = Utf8               LineNumberTable
  #21 = Utf8               main
  #22 = Utf8               ([Ljava/lang/String;)V
  #23 = Utf8               SourceFile
  #24 = Utf8               Test.java
  #25 = NameAndType        #17:#18        // "<init>":()V
  #26 = Utf8               generic/type_safety/Pair
  #27 = Utf8               James
  #28 = Utf8               Jiang
  #29 = NameAndType        #17:#42        // "<init>":(Ljava/lang/Object;Ljava/lang/Object;)V
  #30 = NameAndType        #43:#44        // getFirst:()Ljava/lang/Object;
  #31 = Utf8               java/lang/String
  #32 = Class              #45            // java/lang/System
  #33 = NameAndType        #46:#47        // out:Ljava/io/PrintStream;
  #34 = Utf8               java/lang/StringBuilder
  #35 = Utf8               first:
  #36 = NameAndType        #48:#49        // append:(Ljava/lang/String;)Ljava/lang/StringBuilder;
  #37 = NameAndType        #50:#51        // toString:()Ljava/lang/String;
  #38 = Class              #52            // java/io/PrintStream
  #39 = NameAndType        #53:#54        // println:(Ljava/lang/String;)V
  #40 = Utf8               generic/type_safety/Test
  #41 = Utf8               java/lang/Object
  #42 = Utf8               (Ljava/lang/Object;Ljava/lang/Object;)V
  #43 = Utf8               getFirst
  #44 = Utf8               ()Ljava/lang/Object;
  #45 = Utf8               java/lang/System
  #46 = Utf8               out
  #47 = Utf8               Ljava/io/PrintStream;
  #48 = Utf8               append
  #49 = Utf8               (Ljava/lang/String;)Ljava/lang/StringBuilder;
  #50 = Utf8               toString
  #51 = Utf8               ()Ljava/lang/String;
  #52 = Utf8               java/io/PrintStream
  #53 = Utf8               println
  #54 = Utf8               (Ljava/lang/String;)V
{
  public generic.type_safety.Test();
    descriptor: ()V
    flags: ACC_PUBLIC
    Code:
      stack=1, locals=1, args_size=1
         0: aload_0
         1: invokespecial #1                  // Method java/lang/Object."<init>":()V
         4: return
      LineNumberTable:
        line 9: 0

  public static void main(java.lang.String[]);
    descriptor: ([Ljava/lang/String;)V
    flags: ACC_PUBLIC, ACC_STATIC
    Code:
      stack=4, locals=3, args_size=1
         0: new           #2                  // class generic/type_safety/Pair
         3: dup
         4: ldc           #3                  // String James
         6: ldc           #4                  // String Jiang
         8: invokespecial #5                  // Method generic/type_safety/Pair."<init>":(Ljava/lang/Object;Ljava/lang/Object;)V
        11: astore_1
        12: aload_1
        13: invokevirtual #6                  // Method generic/type_safety/Pair.getFirst:()Ljava/lang/Object;
        16: checkcast     #7                  // class java/lang/String
        19: astore_2
        20: getstatic     #8                  // Field java/lang/System.out:Ljava/io/PrintStream;
        23: new           #9                  // class java/lang/StringBuilder
        26: dup
        27: invokespecial #10                 // Method java/lang/StringBuilder."<init>":()V
        30: ldc           #11                 // String first:
        32: invokevirtual #12                 // Method java/lang/StringBuilder.append:(Ljava/lang/String;)Ljava/lang/StringBuilder;
        35: aload_2
        36: invokevirtual #12                 // Method java/lang/StringBuilder.append:(Ljava/lang/String;)Ljava/lang/StringBuilder;
        39: invokevirtual #13                 // Method java/lang/StringBuilder.toString:()Ljava/lang/String;
        42: invokevirtual #14                 // Method java/io/PrintStream.println:(Ljava/lang/String;)V
        45: return
      LineNumberTable:
        line 11: 0
        line 12: 12
        line 13: 20
        line 14: 45
}
SourceFile: "Test.java"
