Compiled from "Box.java"
public class generic.inheritance.Box<T> {
  public generic.inheritance.Box();
    descriptor: ()V
    Code:
       0: aload_0
       1: invokespecial #1                  // Method java/lang/Object."<init>":()V
       4: return

  public void set(T);
    descriptor: (Ljava/lang/Object;)V
    Code:
       0: aload_0
       1: aload_1
       2: putfield      #2                  // Field t:Ljava/lang/Object;
       5: return

  public T get();
    descriptor: ()Ljava/lang/Object;
    Code:
       0: aload_0
       1: getfield      #2                  // Field t:Ljava/lang/Object;
       4: areturn
}
