Classfile /Users/jiangbenpeng/Documents/demos/java_note/src/generic/inheritance/BoxTest.class
  Last modified Feb 6, 2016; size 800 bytes
  MD5 checksum 105c3cfbb838ba9fcbaead52fa922370
  Compiled from "BoxTest.java"
public class generic.inheritance.BoxTest
  minor version: 0
  major version: 52
  flags: ACC_PUBLIC, ACC_SUPER
Constant pool:
   #1 = Methodref          #11.#24        // java/lang/Object."<init>":()V
   #2 = Fieldref           #25.#26        // java/lang/System.out:Ljava/io/PrintStream;
   #3 = Methodref          #5.#27         // generic/inheritance/Box.get:()Ljava/lang/Object;
   #4 = Methodref          #28.#29        // java/io/PrintStream.println:(Ljava/lang/Object;)V
   #5 = Class              #30            // generic/inheritance/Box
   #6 = Methodref          #5.#24         // generic/inheritance/Box."<init>":()V
   #7 = Methodref          #31.#32        // java/lang/Integer.valueOf:(I)Ljava/lang/Integer;
   #8 = Methodref          #5.#33         // generic/inheritance/Box.set:(Ljava/lang/Object;)V
   #9 = Methodref          #10.#34        // generic/inheritance/BoxTest.boxTest:(Lgeneric/inheritance/Box;)V
  #10 = Class              #35            // generic/inheritance/BoxTest
  #11 = Class              #36            // java/lang/Object
  #12 = Utf8               <init>
  #13 = Utf8               ()V
  #14 = Utf8               Code
  #15 = Utf8               LineNumberTable
  #16 = Utf8               boxTest
  #17 = Utf8               (Lgeneric/inheritance/Box;)V
  #18 = Utf8               Signature
  #19 = Utf8               (Lgeneric/inheritance/Box<Ljava/lang/Number;>;)V
  #20 = Utf8               main
  #21 = Utf8               ([Ljava/lang/String;)V
  #22 = Utf8               SourceFile
  #23 = Utf8               BoxTest.java
  #24 = NameAndType        #12:#13        // "<init>":()V
  #25 = Class              #37            // java/lang/System
  #26 = NameAndType        #38:#39        // out:Ljava/io/PrintStream;
  #27 = NameAndType        #40:#41        // get:()Ljava/lang/Object;
  #28 = Class              #42            // java/io/PrintStream
  #29 = NameAndType        #43:#44        // println:(Ljava/lang/Object;)V
  #30 = Utf8               generic/inheritance/Box
  #31 = Class              #45            // java/lang/Integer
  #32 = NameAndType        #46:#47        // valueOf:(I)Ljava/lang/Integer;
  #33 = NameAndType        #48:#44        // set:(Ljava/lang/Object;)V
  #34 = NameAndType        #16:#17        // boxTest:(Lgeneric/inheritance/Box;)V
  #35 = Utf8               generic/inheritance/BoxTest
  #36 = Utf8               java/lang/Object
  #37 = Utf8               java/lang/System
  #38 = Utf8               out
  #39 = Utf8               Ljava/io/PrintStream;
  #40 = Utf8               get
  #41 = Utf8               ()Ljava/lang/Object;
  #42 = Utf8               java/io/PrintStream
  #43 = Utf8               println
  #44 = Utf8               (Ljava/lang/Object;)V
  #45 = Utf8               java/lang/Integer
  #46 = Utf8               valueOf
  #47 = Utf8               (I)Ljava/lang/Integer;
  #48 = Utf8               set
{
  public generic.inheritance.BoxTest();
    descriptor: ()V
    flags: ACC_PUBLIC
    Code:
      stack=1, locals=1, args_size=1
         0: aload_0
         1: invokespecial #1                  // Method java/lang/Object."<init>":()V
         4: return
      LineNumberTable:
        line 9: 0

  public static void boxTest(generic.inheritance.Box<java.lang.Number>);
    descriptor: (Lgeneric/inheritance/Box;)V
    flags: ACC_PUBLIC, ACC_STATIC
    Code:
      stack=2, locals=1, args_size=1
         0: getstatic     #2                  // Field java/lang/System.out:Ljava/io/PrintStream;
         3: aload_0
         4: invokevirtual #3                  // Method generic/inheritance/Box.get:()Ljava/lang/Object;
         7: invokevirtual #4                  // Method java/io/PrintStream.println:(Ljava/lang/Object;)V
        10: return
      LineNumberTable:
        line 11: 0
        line 12: 10
    Signature: #19                          // (Lgeneric/inheritance/Box<Ljava/lang/Number;>;)V

  public static void main(java.lang.String[]);
    descriptor: ([Ljava/lang/String;)V
    flags: ACC_PUBLIC, ACC_STATIC
    Code:
      stack=2, locals=3, args_size=1
         0: new           #5                  // class generic/inheritance/Box
         3: dup
         4: invokespecial #6                  // Method generic/inheritance/Box."<init>":()V
         7: astore_1
         8: aload_1
         9: bipush        7
        11: invokestatic  #7                  // Method java/lang/Integer.valueOf:(I)Ljava/lang/Integer;
        14: invokevirtual #8                  // Method generic/inheritance/Box.set:(Ljava/lang/Object;)V
        17: aload_1
        18: invokestatic  #9                  // Method boxTest:(Lgeneric/inheritance/Box;)V
        21: new           #5                  // class generic/inheritance/Box
        24: dup
        25: invokespecial #6                  // Method generic/inheritance/Box."<init>":()V
        28: astore_2
        29: aload_2
        30: bipush        8
        32: invokestatic  #7                  // Method java/lang/Integer.valueOf:(I)Ljava/lang/Integer;
        35: invokevirtual #8                  // Method generic/inheritance/Box.set:(Ljava/lang/Object;)V
        38: return
      LineNumberTable:
        line 16: 0
        line 17: 8
        line 18: 17
        line 20: 21
        line 21: 29
        line 23: 38
}
SourceFile: "BoxTest.java"
